my_own_package/__init__.py
my_hello_project-0.1.0.dist-info/METADATA
my_hello_project-0.1.0.dist-info/WHEEL
my_hello_project-0.1.0.dist-info/top_level.txt
my_hello_project-0.1.0.dist-info/RECORD
