Metadata-Version: 2.1
Name: my-hello-project
Version: 0.1.0
Summary: Says Hello to user
Author: Mihai Rarau
Author-email: mihai.rarau@gmail.com
License: UNKNOWN
Platform: UNKNOWN
